pymarcspec/__init__.py
pymarcspec/marcspec.ebnf
pymarcspec/model.py
pymarcspec/parser.py
pymarcspec/search.py
pymarcspec/semantics.py
pymarcspec/textstyle.py
pymarcspec-0.0.3.dist-info/METADATA
pymarcspec-0.0.3.dist-info/WHEEL
pymarcspec-0.0.3.dist-info/entry_points.txt
pymarcspec-0.0.3.dist-info/top_level.txt
pymarcspec-0.0.3.dist-info/RECORD
