Metadata-Version: 2.1
Name: pymarcspec
Version: 0.0.3
Summary: Search pymarc.Record using a string expression
Home-page: https://github.com/danizen/pymarcspec/
Author: Dan Davis
Author-email: dan@danizen.net
License: UNKNOWN
Platform: UNKNOWN
Classifier: Development Status :: 4 - Beta
Classifier: License :: Public Domain
Classifier: Environment :: Console
Classifier: Intended Audience :: Education
Classifier: Intended Audience :: Developers
Classifier: Intended Audience :: Information Technology
Classifier: Operating System :: MacOS :: MacOS X
Classifier: Operating System :: Microsoft :: Windows
Classifier: Operating System :: POSIX
Classifier: Programming Language :: Python :: 3
Classifier: Programming Language :: Python :: 3.6
Classifier: Programming Language :: Python :: 3.7
Classifier: Programming Language :: Python :: 3.8
Classifier: Programming Language :: Python :: 3.9
Classifier: Topic :: Utilities
Classifier: Topic :: Text Processing :: General
Requires-Python: >=3.6
Requires-Dist: attrs
Requires-Dist: lxml
Requires-Dist: pymarc
Requires-Dist: tatsu
